Workbook

Sheet Raw Data
A1: Air India — Financial & Operational Raw Data | Source: Annual Report FY2024
A2: All financial figures in ₹ Millions (standalone) unless noted | Blue = hardcoded input
A3: Particulars | B3: Unit | C3: FY2024 | D3: FY2023 | E3: YoY Change | F3: YoY %
A4: FINANCIAL PERFORMANCE (Standalone — Air India Ltd only)
A5: Revenue from Operations | B5: ₹ Mn | C5: 388124.77 | D5: 313773.68 | E5: =C5-D5 -> 74351.09 | F5: =IF(D5<>0,(C5-D5)/D5,"-") -> 0.2369577
A6: — Passenger Revenue | B6: ₹ Mn | C6: 364033.48 | D6: 290756.31 | E6: =C6-D6 -> 73277.17 | F6: =IF(D6<>0,(C6-D6)/D6,"-") -> 0.25202263
A7: — Cargo Revenue | B7: ₹ Mn | C7: 20371.28 | D7: 19851.43 | E7: =C7-D7 -> 519.85 | F7: =IF(D7<>0,(C7-D7)/D7,"-") -> 0.02618703
A8: — Other Operating Revenue | B8: ₹ Mn | C8: 3720.01 | D8: 3165.94 | E8: =C8-D8 -> 554.07 | F8: =IF(D8<>0,(C8-D8)/D8,"-") -> 0.17500963
A9: Other Income | B9: ₹ Mn | C9: 19636.36 | D9: 9568.92 | E9: =C9-D9 -> 10067.44 | F9: =IF(D9<>0,(C9-D9)/D9,"-") -> 1.0520978
A10: Total Income | B10: ₹ Mn | C10: 407761.13 | D10: 323342.6 | E10: =C10-D10 -> 84418.53 | F10: =IF(D10<>0,(C10-D10)/D10,"-") -> 0.26108075
A12: Aircraft Fuel Expenses | B12: ₹ Mn | C12: 158534.52 | D12: 152989.16 | E12: =C12-D12 -> 5545.36 | F12: =IF(D12<>0,(C12-D12)/D12,"-") -> 0.036246751
A13: Aircraft Repair & Maintenance | B13: ₹ Mn | C13: 66582.73 | D13: 48753.56 | E13: =C13-D13 -> 17829.17 | F13: =IF(D13<>0,(C13-D13)/D13,"-") -> 0.36569986
A14: Airport Fees & Charges | B14: ₹ Mn | C14: 52493.35 | D14: 37982.68 | E14: =C14-D14 -> 14510.67 | F14: =IF(D14<>0,(C14-D14)/D14,"-") -> 0.38203386
A15: Employee Benefit Expenses | B15: ₹ Mn | C15: 40312.64 | D15: 27394.24 | E15: =C15-D15 -> 12918.4 | F15: =IF(D15<>0,(C15-D15)/D15,"-") -> 0.47157359
A16: Finance Costs | B16: ₹ Mn | C16: 25690.63 | D16: 11092.95 | E16: =C16-D16 -> 14597.68 | F16: =IF(D16<>0,(C16-D16)/D16,"-") -> 1.3159421
A17: Depreciation & Amortisation | B17: ₹ Mn | C17: 31172.43 | D17: 30574.57 | E17: =C17-D17 -> 597.86 | F17: =IF(D17<>0,(C17-D17)/D17,"-") -> 0.019554159
... A21: Net Loss | B21: ₹ Mn | C21: -44440.95 | D21: -113879.56 | E21: =C21-D21 -> 69438.61 | F21: =IF(D21<>0,(C21-D21)/D21,"-") -> -0.60975481
A23: OPERATIONAL METRICS (Consolidated Group)
A24: Available Seat Kilometres (ASK) | B24: Mn | C24: 74086 | D24: 60900 | E24: =C24-D24 -> 13186 | F24: =IF(D24<>0,(C24-D24)/D24,"-") -> 0.21651888
A25: Revenue Passenger Kilometres (RPK) | B25: Mn | C25: 63813 | D25: 50462 | E25: =C25-D25 -> 13351 | F25: =IF(D25<>0,(C25-D25)/D25,"-") -> 0.26457532
A26: Passenger Load Factor | B26: % | C26: 0.861 | D26: 0.819 | E26: =C26-D26 -> 0.042 | F26: N/A
A27: Passengers Carried | B27: Mn | C27: 23.5 | D27: 18.5 | E27: =C27-D27 -> 5 | F27: =IF(D27<>0,(C27-D27)/D27,"-") -> 0.27027027
A28: Available Tonne Kilometres (ATK) | B28: Mn | C28: 10009 | D28: 8227 | E28: =C28-D28 -> 1782 | F28: =IF(D28<>0,(C28-D28)/D28,"-") -> 0.21660387
A29: Revenue Tonne Kilometres (RTK) | B29: Mn | C29: 7476 | D29: 5850 | E29: =C29-D29 -> 1626 | F29: =IF(D29<>0,(C29-D29)/D29,"-") -> 0.27794872
A30: Freight Carried | B30: Tonnes | C30: 213696 | D30: 175212 | E30: =C30-D30 -> 38484 | F30: =IF(D30<>0,(C30-D30)/D30,"-") -> 0.21964249
A32: Source: Air India Annual Report FY2023-24 | Standalone P&L (₹ Mn) | Operational metrics consolidated

Sheet Analysis
A1: Air India — Derived Metrics & Benchmark Analysis | Green = linked from Raw Data
A2: Calculated metrics | IndiGo FY24 = actual figures from InterGlobe Aviation Annual Report FY2023-24
A3: Metric | B3: Unit | C3: AI FY24 | D3: AI FY23 | E3: IndiGo FY24 (Actual) | F3: Gap (AI vs IndiGo) | G3: Insight
A4: UNIT ECONOMICS
A5: Yield per RPK | B5: ₹ / RPK | C5: ='Raw Data'!C6/'Raw Data'!C27 -> 15490.786 | D5: ='Raw Data'!D6/'Raw Data'!D27 -> 15716.557 | E5: 5.0811403 | F5: =C5-E5 -> 15485.705 | G5: AI yield ₹5.71 vs IndiGo ₹5.08 — AI earns more per RPK (longer intl routes + premium)
A6: RASK (Revenue per ASK) | B6: ₹ / ASK | C6: ='Raw Data'!C5/'Raw Data'!C26 -> 450783.7 | D6: ='Raw Data'!D5/'Raw Data'!D26 -> 383118.05 | E6: 4.96 | F6: =C6-E6 -> 450778.74 | G6: AI RASK ₹5.24 vs IndiGo ₹4.96 — AI has higher revenue efficiency per seat-km
A7: CASK (Cost per ASK) | B7: ₹ / ASK | C7: ='Raw Data'!C19/'Raw Data'!C26 -> 85466.667 | D7: ='Raw Data'!D19/'Raw Data'!D26 -> 62031.087 | E7: 4.38 | F7: =C7-E7 -> 85462.287 | G7: AI CASK ₹6.10 vs IndiGo ₹4.38 — AI costs 39% more per seat-km; biggest gap to close
A8: Fuel Cost per ASK | B8: ₹ / ASK | C8: ='Raw Data'!C12/'Raw Data'!C26 -> 184128.36 | D8: ='Raw Data'!D12/'Raw Data'!D26 -> 186799.95 | E8: 1.7162842 | F8: =C8-E8 -> 184126.65 | G8: AI fuel CASK ₹2.14 vs IndiGo ₹1.72 — older fleet drives higher fuel burn per seat-km
A9: Load Factor | B9: % | C9: ='Raw Data'!C28 -> 10009 | D9: ='Raw Data'!D28 -> 8227 | E9: 0.859 | F9: =C9-E9 -> 10008.141 | G9: AI 86.1% vs IndiGo 85.9% — nearly identical; both filling planes efficiently
A10: Revenue per Passenger | B10: ₹ | C10: ='Raw Data'!C5/('Raw Data'!C29*1000000) -> 5.1916101e-05 | D10: ='Raw Data'!D5/('Raw Data'!D29*1000000) -> 5.3636526e-05 | E10: 6456.0698 | F10: =C10-E10 -> -6456.0698 | G10: AI ₹16,520 vs IndiGo ₹6,456 per pax — AI serves longer international routes
A12: COST STRUCTURE — % of Total Expenses (FY24)
A13: Aircraft Fuel | B13: % of costs | C13: ='Raw Data'!C12/'Raw Data'!C19 -> 2.154388 | E13: 0.37831677 | G13: AI 35.1% vs IndiGo 37.8% — IndiGo more fuel-exposed despite newer fleet (scale effect)
A14: Aircraft Repair & Maint. | B14: % of costs | C14: ='Raw Data'!C13/'Raw Data'!C19 -> 0.90481893 | E14: 0.15717909 | G14: AI 14.7% vs IndiGo 15.7% — comparable maintenance burden
A15: Airport Fees & Charges | B15: % of costs | C15: ='Raw Data'!C14/'Raw Data'!C19 -> 0.7133528 | E15: 0.073179086 | G15: AI 11.6% vs IndiGo 7.3% — AI pays proportionally far more in airport charges
A16: Employee Benefits | B16: % of costs | C16: ='Raw Data'!C15/'Raw Data'!C19 -> 0.54782434 | E16: 0.092388628 | G16: AI 8.9% vs IndiGo 9.2% — employee cost share similar; AI hiring aggressively
A17: Finance Costs | B17: % of costs | C17: ='Raw Data'!C16/'Raw Data'!C19 -> 0.34912009 | E17: 0.06598469 | G17: AI 5.7% vs IndiGo 6.6% — both carry heavy finance costs (leases + debt)
A18: Depreciation | B18: % of costs | C18: ='Raw Data'!C17/'Raw Data'!C19 -> 0.42361443 | E18: 0.10137595 | G18: AI 6.9% vs IndiGo 10.1% — IndiGo's newer fleet = higher depreciation charge
A19: Other Expenses | B19: % of costs | C19: ='Raw Data'!C21/'Raw Data'!C19 -> -0.60392557 | E19: 0.097789434
A21: PROFITABILITY RATIOS
A22: Operating Margin | B22: % | C22: =('Raw Data'!C5+'Raw Data'!C19*-1)/'Raw Data'!C5 -> 0.81040427 | D22: =('Raw Data'!D5+'Raw Data'!D19*-1)/'Raw Data'!D5 -> 0.83808884 | E22: 0.082979807 | G22: AI -11.1% vs IndiGo +8.3% op margin — the transformation gap; AI still loss-making
A23: Revenue Growth (YoY) | B23: % | C23: =('Raw Data'!C5-'Raw Data'!D5)/'Raw Data'!D5 -> 0.2369577 | D23: N/A | E23: 0.26554327 | G23: AI +24% vs IndiGo +26.5% rev growth — both strong; IndiGo slightly faster
A24: Cost Growth (YoY) | B24: % | C24: =('Raw Data'!C19-'Raw Data'!D19)/'Raw Data'!D19 -> 0.4484604 | D24: N/A | E24: 0.12442599 | G24: AI +22% vs IndiGo +12.4% cost growth — AI adding capacity + people faster
A25: Fuel as % of Revenue | B25: % | C25: ='Raw Data'!C12/'Raw Data'!C5 -> 0.40846277 | D25: ='Raw Data'!D12/'Raw Data'!D5 -> 0.48757805 | E25: 0.34692412 | G25: AI 40.8% vs IndiGo 34.7% fuel/rev — AI more exposed to ATF price risk
A27: * IndiGo benchmarks are indicative estimates. Update with InterGlobe Aviation FY24 Annual Report for precise comparison.

Sheet Scenario Analysis
A1: Air India — Scenario Analysis: What-If on Load Factor & Yield
A2: Change the yellow assumption cells to model different scenarios | All figures ₹ Millions
A4: BASE INPUTS (from FY24 Actuals)
A5: Base Revenue from Operations (₹ Mn) | B5: ='Raw Data'!C5 -> 388124.77
A6: Base Passenger Revenue (₹ Mn) | B6: ='Raw Data'!C6 -> 364033.48
A7: Base ASK (Mn) | B7: ='Raw Data'!C26 -> 0.861
A8: Base RPK (Mn) | B8: ='Raw Data'!C27 -> 23.5
A9: Base Load Factor (%) | B9: ='Raw Data'!C28 -> 10009
A10: Base Passengers Carried (Mn) | B10: ='Raw Data'!C29 -> 7476
A11: Base Total Expenses (₹ Mn) | B11: ='Raw Data'!C19 -> 73586.8
A12: Base Net Loss (₹ Mn) | B12: ='Raw Data'!C20 -> 452202.08
A14: SCENARIO ASSUMPTIONS (Yellow cells = change these)
A15: Assumption | C15: Bear Case | D15: Base Case | E15: Bull Case | F15: Notes
A16: Load Factor Improvement | B16: -0.02 | C16: 0 | D16: 0.03 | E16: % pt change vs FY24 86.1%
A17: Yield Improvement (per RPK) | B17: -0.05 | C17: 0 | D17: 0.08 | E17: % change in yield
A18: ASK Growth | B18: 0.1 | C18: 0.15 | D18: 0.22 | E18: % capacity expansion
A19: Cost Growth Rate | B19: 0.12 | C19: 0.1 | D19: 0.07 | E19: % increase in total costs
A20: Fuel Price Change | B20: 0.08 | C20: 0 | D20: -0.05 | E20: % change in ATF price
A22: SCENARIO OUTPUT — Impact on Revenue & Loss
A23: Output Metric | B23: Bear Case | C23: Base Case | D23: Bull Case | E23: Variance (Bull-Bear)
A24: Projected ASK (Mn) | B24: =B7*(1+B18) -> 0.9471 | C24: =B7*(1+C18) -> 0.99015 | D24: =B7*(1+D18) -> 1.05042 | E24: =D24-B24 -> 0.10332
A25: Projected Load Factor (%) | B25: =B9+B16 -> 10008.98 | C25: =B9+C16 -> 10009 | D25: =B9+D16 -> 10009.03 | E25: =D25-B25 -> 0.05
A26: Projected RPK (Mn) | B26: =B7*(1+B18)*(B9+B16) -> 9479.505 | C26: =B7*(1+C18)*(B9+C16) -> 9910.4114 | D26: =B7*(1+D18)*(B9+D16) -> 10513.685 | E26: =D26-B26 -> 1034.1803
A27: Projected Passenger Revenue (₹ Mn) | B27: =B6*(1+B17)*(B7*(1+B18)*(B9+B16))/B8 -> 1.3950274e+08 | C27: =B6*(1+C17)*(B7*(1+C18)*(B9+C16))/B8 -> 1.5352007e+08 | D27: =B6*(1+D17)*(B7*(1+D18)*(B9+D16))/B8 -> 1.7589447e+08 | E27: =D27-B27 -> 36391736
A28: Projected Total Expenses (₹ Mn) | B28: =B11*(1+B19) -> 82417.216 | C28: =B11*(1+C19) -> 80945.48 | D28: =B11*(1+D19) -> 78737.876 | E28: =D28-B28 -> -3679.34
A29: Projected Net Loss (₹ Mn) | B29: =B27-B28 -> 1.3942032e+08 | C29: =C27-C28 -> 1.5343912e+08 | D29: =D27-D28 -> 1.7581574e+08 | E29: =D29-B29 -> 36395416
A31: Note: Scenarios model impact of operational improvements. Costs assumed to grow with capacity.

Sheet Dashboard
A1: Air India — Business Performance Dashboard | FY2023 vs FY2024
A2: Post-privatisation transformation analysis | Source: Air India Annual Report FY2024
A3: KEY PERFORMANCE INDICATORS — FY2024
A4: Revenue (₹ Mn) | D4: Net Loss (₹ Mn) | G4: Load Factor | J4: Passengers (Mn) | M4: Revenue Growth
A5: ='Raw Data'!C5 -> 388124.77 | D5: ='Raw Data'!C20 -> 452202.08 | G5: ='Raw Data'!C28 -> 10009 | J5: ='Raw Data'!C29 -> 7476 | M5: =('Raw Data'!C5-'Raw Data'!D5)/'Raw Data'!D5 -> 0.2369577
A44: KEY FINDINGS & RECOMMENDATIONS
A45: # | B45: Finding | E45: Data Point | H45: Recommendation
A46: 1 | B46: Loss narrowing significantly | E46: Loss reduced from ₹1,13,879 Mn to ₹44,441 Mn (-61%) | H46: Continue cost discipline; prioritise CASK reduction to reach breakeven by FY26
A47: 2 | B47: Fuel dominates cost base | E47: Fuel = 35.1% of total expenses (₹1,58,534 Mn) | H47: Accelerate new aircraft induction (A320neo, B787) to improve fuel efficiency
A48: 3 | B48: Load factor improved strongly | E48: 86.1% in FY24 vs 81.9% in FY23 — approaching IndiGo levels | H48: Optimise route mix for yield improvement; focus on high-margin international routes
A49: 4 | B49: Revenue growing faster than costs | E49: Revenue +24% YoY; Expenses +22% YoY | H49: Sustain pricing power through premium product investment and loyalty programme
A50: 5 | B50: Employee cost rising rapidly | E50: Employee expenses up 47% YoY (9,000+ new hires) | H50: Improve revenue per employee ratio; leverage technology for operational efficiency
A51: FY2023 | B51: ='Raw Data'!D5 -> 313773.68 | C51: ='Raw Data'!D19 -> 50803.46 | D51: ='Raw Data'!D20 -> 371118.33 | F51: FY2023 | G51: ='Raw Data'!D28 -> 8227 | I51: Fuel | J51: ='Raw Data'!C12 -> 158534.52 | L51: FY2023 | M51: ='Raw Data'!D29 -> 5850
A52: FY2024 | B52: ='Raw Data'!C5 -> 388124.77 | C52: ='Raw Data'!C19 -> 73586.8 | D52: ='Raw Data'!C20 -> 452202.08 | F52: FY2024 | G52: ='Raw Data'!C28 -> 10009 | I52: Repair & Maint. | J52: ='Raw Data'!C13 -> 66582.73 | L52: FY2024 | M52: ='Raw Data'!C29 -> 7476
I53: Airport Fees | J53: ='Raw Data'!C14 -> 52493.35
I54: Employee | J54: ='Raw Data'!C15 -> 40312.64
I55: Finance | J55: ='Raw Data'!C16 -> 25690.63
I56: Depreciation | J56: ='Raw Data'!C17 -> 31172.43
I57: Other | J57: ='Raw Data'!C21 -> -44440.95

Sheet IndiGo Raw Data
A1: IndiGo (InterGlobe Aviation) — FY2023-24 | Source: Annual Report FY2023-24
A2: All figures ₹ Millions (standalone) | Blue = input from annual report
A3: Particulars | B3: Unit | C3: FY2024 | D3: FY2023 | E3: YoY Change | F3: YoY %
A4: FINANCIAL PERFORMANCE (₹ Millions, Standalone)
A5: Revenue from Operations | B5: ₹ Mn | C5: 689043.42 | D5: 544464.53 | E5: =C5-D5 -> 144578.89 | F5: =IF(D5<>0,(C5-D5)/ABS(D5),"-") -> 0.26554327
A6: — Passenger Ticket Revenue | B6: ₹ Mn | C6: 608227.74 | D6: 481743.71 | E6: =C6-D6 -> 126484.03 | F6: =IF(D6<>0,(C6-D6)/ABS(D6),"-") -> 0.26255461
A7: — Ancillary Revenue | B7: ₹ Mn | C7: 65789.01 | D7: 54415.21 | E7: =C7-D7 -> 11373.8 | F7: =IF(D7<>0,(C7-D7)/ABS(D7),"-") -> 0.20901877
A8: Other Income | B8: ₹ Mn | C8: 23255.72 | D8: 14314.35 | E8: =C8-D8 -> 8941.37 | F8: =IF(D8<>0,(C8-D8)/ABS(D8),"-") -> 0.6246438
A9: Total Income | B9: ₹ Mn | C9: 712299.14 | D9: 558778.88 | E9: =C9-D9 -> 153520.26 | F9: =IF(D9<>0,(C9-D9)/ABS(D9),"-") -> 0.27474242
A11: Aircraft Fuel Expenses | B11: ₹ Mn | C11: 239045.78 | D11: 236460.17 | E11: =C11-D11 -> 2585.61 | F11: =IF(D11<>0,(C11-D11)/ABS(D11),"-") -> 0.010934653
A12: Aircraft & Engine Rentals | B12: ₹ Mn | C12: 10751.95 | D12: 3258.4 | E12: =C12-D12 -> 7493.55 | F12: =IF(D12<>0,(C12-D12)/ABS(D12),"-") -> 2.2997637
A13: Supplementary Rentals & Maintenance | B13: ₹ Mn | C13: 99316.24 | D13: 80449.6 | E13: =C13-D13 -> 18866.64 | F13: =IF(D13<>0,(C13-D13)/ABS(D13),"-") -> 0.23451503
A14: Airport Fees & Charges | B14: ₹ Mn | C14: 46239.43 | D14: 36468 | E14: =C14-D14 -> 9771.43 | F14: =IF(D14<>0,(C14-D14)/ABS(D14),"-") -> 0.26794532
A15: Employee Benefits Expense | B15: ₹ Mn | C15: 58377.3 | D15: 43246.56 | E15: =C15-D15 -> 15130.74 | F15: =IF(D15<>0,(C15-D15)/ABS(D15),"-") -> 0.34987153
A16: Finance Costs | B16: ₹ Mn | C16: 41693.53 | D16: 31317.31 | E16: =C16-D16 -> 10376.22 | F16: =IF(D16<>0,(C16-D16)/ABS(D16),"-") -> 0.33132539
A17: Depreciation & Amortisation | B17: ₹ Mn | C17: 64056.09 | D17: 51012.37 | E17: =C17-D17 -> 13043.72 | F17: =IF(D17<>0,(C17-D17)/ABS(D17),"-") -> 0.2556972
... A21: Net Profit / (Loss) | B21: ₹ Mn | C21: 81674.85 | D21: -3167.16 | E21: =C21-D21 -> 84842.01 | F21: =IF(D21<>0,(C21-D21)/ABS(D21),"-") -> 26.78804
A23: OPERATIONAL METRICS
A24: Available Seat Kilometres (ASK) | B24: Mn | C24: 139281 | D24: 114359 | E24: =C24-D24 -> 24922 | F24: =IF(D24<>0,(C24-D24)/ABS(D24),"-") -> 0.21792775
A25: Revenue Passenger Kilometres (RPK) | B25: Mn | C25: 119703 | D25: 93889 | E25: =C25-D25 -> 25814 | F25: =IF(D25<>0,(C25-D25)/ABS(D25),"-") -> 0.27494169
A26: Passenger Load Factor | B26: % | C26: 0.859 | D26: 0.821 | E26: =C26-D26 -> 0.038 | F26: =IF(D26<>0,(C26-D26)/ABS(D26),"-") -> 0.046285018
A27: Passengers Carried | B27: Thousands | C27: 106728 | D27: 85591 | E27: =C27-D27 -> 21137 | F27: =IF(D27<>0,(C27-D27)/ABS(D27),"-") -> 0.24695353
A28: Number of Aircraft | B28: Units | C28: 367 | D28: 304 | E28: =C28-D28 -> 63 | F28: =IF(D28<>0,(C28-D28)/ABS(D28),"-") -> 0.20723684
A29: RASK | B29: ₹/ASK | C29: 4.96 | D29: 4.8 | E29: =C29-D29 -> 0.16 | F29: =IF(D29<>0,(C29-D29)/ABS(D29),"-") -> 0.033333333
A30: CASK | B30: ₹/ASK | C30: 4.38 | D30: 4.83 | E30: =C30-D30 -> -0.45 | F30: =IF(D30<>0,(C30-D30)/ABS(D30),"-") -> -0.093167702
A31: CASK Ex-Fuel | B31: ₹/ASK | C31: 2.66 | D31: 2.76 | E31: =C31-D31 -> -0.1 | F31: =IF(D31<>0,(C31-D31)/ABS(D31),"-") -> -0.036231884
A32: EBITDAR Margin | B32: % | C32: 0.255 | D32: 0.134 | E32: =C32-D32 -> 0.121 | F32: =IF(D32<>0,(C32-D32)/ABS(D32),"-") -> 0.90298507
A33: Net Profit Margin | B33: % | C33: 0.119 | D33: -0.006 | E33: =C33-D33 -> 0.125 | F33: =IF(D33<>0,(C33-D33)/ABS(D33),"-") -> 20.833333
A35: Source: InterGlobe Aviation Ltd Annual Report FY2023-24 | Standalone P&L | ₹ Millions
